LICENSE
MANIFEST.in
README.rst
setup.py
dj_paas_env/__init__.py
dj_paas_env/database.py
dj_paas_env/provider.py
dj_paas_env/static.py
dj_paas_env/test.py
dj_paas_env.egg-info/PKG-INFO
dj_paas_env.egg-info/SOURCES.txt
dj_paas_env.egg-info/dependency_links.txt
dj_paas_env.egg-info/top_level.txt